PySFS/__init__.py
PySFS/api_get.py
PySFS/api_post.py
PySFS/client.py
pysfs-0.1.3.dist-info/METADATA
pysfs-0.1.3.dist-info/WHEEL
pysfs-0.1.3.dist-info/top_level.txt
pysfs-0.1.3.dist-info/RECORD
