Metadata-Version: 2.4
Name: PySFS
Version: 0.1.3
Summary: Python client for SFSControl Mod Server API
Author-email: DarkSpaceY <yif.chien.nolimit@gmail.com>
License-Expression: MIT
Classifier: Programming Language :: Python :: 3
Classifier: Operating System :: OS Independent
Requires-Python: >=3.6
Requires-Dist: requests>=2.27
